{
    "prediction_strategies": {
        "simple_rsi": {
            "rsi_period": 18,
            "rsi_overbought": 80,
            "rsi_oversold": 20
        },
        "micro_trend_momentum": {
            "ema_period": 5,
            "volume_sma_period": 5,
            "min_volume_factor": 1,
            "rsi_filter_period": 14,
            "rsi_extreme_ob": 85,
            "rsi_extreme_os": 15
        },
        "rsi_sma": {
            "rsi_period": 18,
            "rsi_overbought": 80,
            "rsi_oversold": 20,
            "sma_period": 30
        }
    },
    "investment_strategies": {
        "fixed": {
            "amount": 20
        },
        "percentage_of_balance": {
            "percentageOfBalance": 10
        }
    }
}